CHANGELOG
LICENSE
MANIFEST.in
README.rst
setup.py
natto/__init__.py
natto/api.py
natto/binding.py
natto/dictionary.py
natto/environment.py
natto/mecab.py
natto/node.py
natto/option_parse.py
natto/support.py
natto/version.py
natto_py_fork.egg-info/PKG-INFO
natto_py_fork.egg-info/SOURCES.txt
natto_py_fork.egg-info/dependency_links.txt
natto_py_fork.egg-info/not-zip-safe
natto_py_fork.egg-info/requires.txt
natto_py_fork.egg-info/top_level.txt
tests/__init__.py
tests/test_binding.py
tests/test_dictionary.py
tests/test_environment.py
tests/test_mecab.py
tests/test_option_parse.py
tests/test_suite.py
tests/test_support.py