Metadata-Version: 1.1
Name: natto-py-fork
Version: 0.9.0
Summary: A Tasty Python Binding with MeCab(FFI-based, no SWIG or compiler necessary)
Home-page: https://github.com/kissge/natto-py
Author: kissge
Author-email: mail@yusuk.eki.do
License: BSD
Keywords: MeCab 和布蕪 納豆 Japanese morphological analyzer NLP 形態素解析 自然言語処理 FFI binding バインディング
Platform: UNKNOWN
Classifier: Development Status :: 4 - Beta
Classifier: Intended Audience :: Developers
Classifier: Intended Audience :: Science/Research
Classifier: Topic :: Software Development :: Libraries :: Python Modules
Classifier: Topic :: Text Processing :: Linguistic
Classifier: Natural Language :: Japanese
Classifier: License :: OSI Approved :: BSD License
Classifier: Operating System :: POSIX :: BSD
Classifier: Operating System :: POSIX :: Linux
Classifier: Operating System :: MacOS :: MacOS X
Classifier: Operating System :: Microsoft :: Windows
Classifier: Programming Language :: Python :: 2
Classifier: Programming Language :: Python :: 2.7
Classifier: Programming Language :: Python :: 3
Classifier: Programming Language :: Python :: 3.2
Classifier: Programming Language :: Python :: 3.3
Classifier: Programming Language :: Python :: 3.4
Classifier: Programming Language :: Python :: 3.5
Classifier: Programming Language :: Python :: 3.6
